midtry/__init__.py
midtry/cli.py
midtry/runner.py
midtry/data/__init__.py
midtry/data/protocol.md
midtry-0.1.0.dist-info/METADATA
midtry-0.1.0.dist-info/WHEEL
midtry-0.1.0.dist-info/entry_points.txt
midtry-0.1.0.dist-info/licenses/LICENSE
midtry-0.1.0.dist-info/RECORD
