Metadata-Version: 2.4
Name: midtry
Version: 0.1.0
Summary: Multi-perspective reasoning harness for coding decisions.
Project-URL: Homepage, https://github.com/Hmbown/midtry
Project-URL: Repository, https://github.com/Hmbown/midtry
Project-URL: Documentation, https://github.com/Hmbown/midtry#readme
Project-URL: Issues, https://github.com/Hmbown/midtry/issues
Author-email: Hunter Bown <hunter@midtry.dev>
License: MIT License
License-File: LICENSE
Keywords: cli,inference,llm,multi-agent,reasoning
Classifier: Development Status :: 3 - Alpha
Classifier: Environment :: Console
Classifier: Intended Audience :: Developers
Classifier: License :: OSI Approved :: MIT License
Classifier: Operating System :: OS Independent
Classifier: Programming Language :: Python :: 3
Classifier: Programming Language :: Python :: 3.10
Classifier: Programming Language :: Python :: 3.11
Classifier: Programming Language :: Python :: 3.12
Classifier: Programming Language :: Python :: 3.13
Classifier: Topic :: Software Development :: Libraries :: Python Modules
Classifier: Typing :: Typed
Requires-Python: >=3.10
Requires-Dist: rich>=13.0.0
Requires-Dist: tomli>=2.0.0; python_version < '3.11'
Requires-Dist: typer>=0.12.0
Provides-Extra: dev
Requires-Dist: mypy>=1.10.0; extra == 'dev'
Requires-Dist: pytest-asyncio>=0.24.0; extra == 'dev'
Requires-Dist: pytest>=8.0.0; extra == 'dev'
Requires-Dist: ruff>=0.5.0; extra == 'dev'
